azure/mgmt/synapse/__init__.py
azure/mgmt/synapse/_configuration.py
azure/mgmt/synapse/_synapse_management_client.py
azure/mgmt/synapse/_version.py
azure/mgmt/synapse/aio/__init__.py
azure/mgmt/synapse/aio/_configuration.py
azure/mgmt/synapse/aio/_synapse_management_client.py
azure/mgmt/synapse/aio/operations/__init__.py
azure/mgmt/synapse/aio/operations/_big_data_pools_operations.py
azure/mgmt/synapse/aio/operations/_data_masking_policies_operations.py
azure/mgmt/synapse/aio/operations/_data_masking_rules_operations.py
azure/mgmt/synapse/aio/operations/_extended_sql_pool_blob_auditing_policies_operations.py
azure/mgmt/synapse/aio/operations/_integration_runtime_auth_keys_operations.py
azure/mgmt/synapse/aio/operations/_integration_runtime_connection_infos_operations.py
azure/mgmt/synapse/aio/operations/_integration_runtime_credentials_operations.py
azure/mgmt/synapse/aio/operations/_integration_runtime_monitoring_data_operations.py
azure/mgmt/synapse/aio/operations/_integration_runtime_node_ip_address_operations.py
azure/mgmt/synapse/aio/operations/_integration_runtime_nodes_operations.py
azure/mgmt/synapse/aio/operations/_integration_runtime_object_metadata_operations.py
azure/mgmt/synapse/aio/operations/_integration_runtime_status_operations.py
azure/mgmt/synapse/aio/operations/_integration_runtimes_operations.py
azure/mgmt/synapse/aio/operations/_ip_firewall_rules_operations.py
azure/mgmt/synapse/aio/operations/_keys_operations.py
azure/mgmt/synapse/aio/operations/_libraries_operations.py
azure/mgmt/synapse/aio/operations/_library_operations.py
azure/mgmt/synapse/aio/operations/_operations.py
azure/mgmt/synapse/aio/operations/_private_endpoint_connections_operations.py
azure/mgmt/synapse/aio/operations/_private_endpoint_connections_private_link_hub_operations.py
azure/mgmt/synapse/aio/operations/_private_link_hub_private_link_resources_operations.py
azure/mgmt/synapse/aio/operations/_private_link_hubs_operations.py
azure_mgmt_synapse-2.0.0.dist-info/METADATA
azure_mgmt_synapse-2.0.0.dist-info/WHEEL
azure_mgmt_synapse-2.0.0.dist-info/top_level.txt
azure_mgmt_synapse-2.0.0.dist-info/RECORD
